housing_forecast/__init__.py
housing_forecast/predict.py
Housing_Forecast-2.0.dist-info/METADATA
Housing_Forecast-2.0.dist-info/WHEEL
Housing_Forecast-2.0.dist-info/top_level.txt
Housing_Forecast-2.0.dist-info/RECORD
